Metadata-Version: 2.1
Name: sempack
Version: 0.0.1
Summary: My Package
Author: Semin
Author-email: seminpetr4@gmail.com
